README.md
setup.py
usetime/__init__.py
usetime.egg-info/PKG-INFO
usetime.egg-info/SOURCES.txt
usetime.egg-info/dependency_links.txt
usetime.egg-info/entry_points.txt
usetime.egg-info/top_level.txt